LICENSE
MANIFEST.in
README.md
pyproject.toml
setup.py
DEGA/SIDE.py
DEGA/__init__.py
DEGA/core.py
DEGA/countsTranformers.py
DEGA/dispersions.py
DEGA/logger.py
DEGA/plots.py
DEGA/refit.py
DEGA/statisticalTests.py
DEGA/utils.py
DEGA.egg-info/PKG-INFO
DEGA.egg-info/SOURCES.txt
DEGA.egg-info/dependency_links.txt
DEGA.egg-info/requires.txt
DEGA.egg-info/top_level.txt
DEGA/cython/estimateDispersion.cpp
DEGA/cython/estimateDispersion.pyx
DEGA/cython/negativeBinomialGLM.cpp
DEGA/cython/negativeBinomialGLM.pyx