Metadata-Version: 2.1
Name: DEGA
Version: 0.2.1
Summary: DEGA: a Python package for differential gene expression analysis
Author-email: Luca Menestrina <luca.menestrina@protonmail.com>
License: GNU GENERAL PUBLIC LICENSE
Project-URL: homepage, https://github.com/LucaMenestrina/DEGA
Project-URL: source, https://github.com/LucaMenestrina/DEGA
Project-URL: tracker, https://github.com/LucaMenestrina/DEGA/issues
Classifier: Programming Language :: Python
Classifier: Programming Language :: Python :: 3
Classifier: Programming Language :: Python :: 3 :: Only
Classifier: Programming Language :: Cython
Classifier: License :: OSI Approved :: GNU General Public License v3 or later (GPLv3+)
Classifier: Operating System :: OS Independent
Classifier: Topic :: Scientific/Engineering :: Bio-Informatics
Classifier: Intended Audience :: Education
Classifier: Intended Audience :: Science/Research
Requires-Python: >=3.8
License-File: LICENSE
Requires-Dist: matplotlib>=3.7.2
Requires-Dist: networkx>=3.1
Requires-Dist: numpy>=1.24.4
Requires-Dist: pandas>=2.0.3
Requires-Dist: patsy>=0.5.3
Requires-Dist: scikit-learn>=1.3.0
Requires-Dist: scipy>=1.10.1
Requires-Dist: seaborn>=0.12.2
Requires-Dist: statsmodels>=0.14.0
Requires-Dist: tqdm>=4.64.1
